shap_bpt/__init__.py
shap_bpt/bpt.c
shap_bpt/bpt.cp39-win_amd64.pyd
shap_bpt/bpt.pyx
shap_bpt/shap_bpt.py
shap_bpt-1.0.1.dist-info/licenses/LICENSE
shap_bpt-1.0.1.dist-info/METADATA
shap_bpt-1.0.1.dist-info/WHEEL
shap_bpt-1.0.1.dist-info/top_level.txt
shap_bpt-1.0.1.dist-info/RECORD
