Metadata-Version: 2.4
Name: shap-bpt
Version: 1.0.1
Summary: A python library to compute Shapley image explanations with data-aware Binary Partition Trees
Author-email: "Elvio G. Amparore" <elviogilberto.amparore@unito.it>, Muhammad Rashid <muhammad.rashid@unito.it>
Maintainer-email: Muhammad Rashid <muhammadrashid8045@gmail.com>
License: MIT
Project-URL: Homepage, https://github.com/amparore/shap_bpt
Project-URL: Shapbpt-Tests, https://github.com/rashidrao-pk/shap_bpt_tests
Project-URL: Documentation, https://github.com/amparore/shap_bpt#readme
Project-URL: Issues, https://github.com/amparore/shap_bpt/issues
Project-URL: Paper, https://arxiv.org/abs/XXXX.XXXXX
Project-URL: AAAI, https://aaai.org/aaai26/
Keywords: explainable-ai,xai,shapley-values,computer-vision,interpretability,binary-partition-tree
Classifier: Development Status :: 4 - Beta
Classifier: Intended Audience :: Science/Research
Classifier: License :: OSI Approved :: MIT License
Classifier: Programming Language :: Python :: 3
Classifier: Programming Language :: Python :: 3.9
Classifier: Programming Language :: Python :: 3.10
Classifier: Programming Language :: Python :: 3.11
Classifier: Programming Language :: Python :: 3.12
Classifier: Topic :: Scientific/Engineering :: Artificial Intelligence
Classifier: Operating System :: OS Independent
Requires-Python: >=3.8
License-File: LICENSE
Requires-Dist: torch
Requires-Dist: torchvision
Requires-Dist: numpy
Requires-Dist: pillow
Requires-Dist: matplotlib
Requires-Dist: timm
Requires-Dist: tqdm
Requires-Dist: scikit-image
Requires-Dist: scikit-learn
Dynamic: license-file
